fast_cd_pyb.cpython-310-x86_64-linux-gnu.so
fast_cd_pyb.libs/libOpenGL-b706661f.so.0.0.0
fast_cd_pyb.libs/libGLdispatch-dcc1ca97.so.0.0.0
fast_cd/rig_geometry.py
fast_cd/vectorized_trace.py
fast_cd/complementary_constraint_matrix.py
fast_cd/laplacian_eigenmodes.py
fast_cd/mediapipe_face.py
fast_cd/orthonormalize.py
fast_cd/average_onto_simplex.py
fast_cd/normalize_height_and_center.py
fast_cd/lbs_weight_space_constraint.py
fast_cd/vectorized_transpose.py
fast_cd/rig_curve_geometry.py
fast_cd/deformation_jacobian.py
fast_cd/laplacian.py
fast_cd/project_to_orthogonal.py
fast_cd/closest_orthogonal_subspace.py
fast_cd/read_rig_from_json.py
fast_cd/diffuse_weights.py
fast_cd/arap_hessian.py
fast_cd/project_into_subspace.py
fast_cd/mediapipe_face_captor.py
fast_cd/read_rig_anim_from_json.py
fast_cd/skinning_subspace.py
fast_cd/momentum_leaking_matrix.py
fast_cd/face_landmarks_to_positions.py
fast_cd/lbs_jacobian.py
fast_cd/umfpack_lu_solve.py
fast_cd/fast_cd_sim.py
fast_cd/project_out_subspace.py
fast_cd/world2rel.py
fast_cd/linear_elasticity_hessian.py
fast_cd/cluster_centroids.py
fast_cd/rotate_rig.py
fast_cd/one_euro_filter.py
fast_cd/skinning_clusters.py
fast_cd/cluster_grouping_matrices.py
fast_cd/eigs.py
fast_cd/ympr_to_lame.py
fast_cd/__init__.py
fast_cd/apps/test_FAST_IK_tex.py
fast_cd/apps/animate_rig.py
fast_cd/apps/cd_demo_pose_tracker.py
fast_cd/apps/test_FAST_IK.py
fast_cd/apps/interactive_cd_face_tracking.py
fast_cd/apps/interactive_cd_affine_handle.py
fast_cd/apps/interactive_cd_rig_anim.py
fast_cd/apps/test_FAST_IK_CD_tex.py
fast_cd/apps/__init__.py
fast_cd/shaders/vertex_shader_8.glsl
fast_cd/shaders/vertex_shader_16.glsl
fast_cd/shaders/fragment_shader.glsl
fast_cd/shaders/vertex_shader_4.glsl
fast_cd/shaders/__init__.py
fast_cd/viewers/WeightsViewer.py
fast_cd/viewers/interactive_handle_subspace_viewer.py
fast_cd/viewers/interactive_handle_viewer.py
fast_cd/viewers/ClustersViewer.py
fast_cd_pyb-0.0.5.dist-info/RECORD
fast_cd_pyb-0.0.5.dist-info/top_level.txt
fast_cd_pyb-0.0.5.dist-info/WHEEL
fast_cd_pyb-0.0.5.dist-info/METADATA
