Metadata-Version: 2.1
Name: fast-cd-pyb
Version: 0.0.5
Home-page: https://github.com/otmanon/fast-cd-pyb/
Author: Otman Benchekroun
Author-email: otmanbench@gmail.com
License: MIT
Requires-Dist: packaging
Requires-Dist: numpy
Requires-Dist: scipy
Requires-Dist: cvxopt
Requires-Dist: polyscope
Requires-Dist: libigl
Requires-Dist: scikit-learn
